[
  {
    "masanpham": "SP01",
    "tensanpham": "Laptop Dell XPS 13",
    "soluong": 10,
    "giatri": 32000000,
    "tinhchat": "\u0110i\u1EC7n t\u1EED"
  },
  {
    "masanpham": "SP02",
    "tensanpham": "Chu\u1ED9t Logitech G Pro",
    "soluong": 25,
    "giatri": 700000,
    "tinhchat": "Ph\u1EE5 ki\u1EC7n"
  },
  {
    "masanpham": "SP03",
    "tensanpham": "B\u00E0n ph\u00EDm Razer BlackWidow",
    "soluong": 15,
    "giatri": 1500000,
    "tinhchat": "Ph\u1EE5 ki\u1EC7n"
  },
  {
    "masanpham": "SP04",
    "tensanpham": "Tai nghe Sony WH-1000XM5",
    "soluong": 12,
    "giatri": 2000000,
    "tinhchat": "\u00C2m thanh"
  },
  {
    "masanpham": "SP05",
    "tensanpham": "M\u00E0n h\u00ECnh LG UltraWide 29\u0027\u0027",
    "soluong": 5,
    "giatri": 6500000,
    "tinhchat": "\u0110i\u1EC7n t\u1EED"
  }
]